pandaspg/__init__.py
pandaspg/main.py
pandaspg-0.0.3.3.dist-info/LICENSE
pandaspg-0.0.3.3.dist-info/METADATA
pandaspg-0.0.3.3.dist-info/WHEEL
pandaspg-0.0.3.3.dist-info/top_level.txt
pandaspg-0.0.3.3.dist-info/RECORD
