Metadata-Version: 2.1
Name: pandaspg
Version: 0.0.3.3
Summary: This library contains several functions that allow you to migrate data from a CSV file or Pandas Dataframe into a PostgreSQL database using the libraries Psycopg2 and Pandas
Author-email: Adolfo Jimenez <adolfoj@protonmail.com>
Project-URL: Homepage, https://github.com/eadwulf/pandaspg
Project-URL: Bug Tracker, https://github.com/eadwulf/pandaspg/issues
Classifier: Programming Language :: Python :: 3
Classifier: License :: OSI Approved :: MIT License
Classifier: Operating System :: OS Independent
Requires-Python: >=3.10
License-File: LICENSE
